README.rst
setup.py
sanic/__init__.py
sanic/__main__.py
sanic/app.py
sanic/blueprints.py
sanic/config.py
sanic/constants.py
sanic/cookies.py
sanic/exceptions.py
sanic/handlers.py
sanic/log.py
sanic/request.py
sanic/response.py
sanic/router.py
sanic/server.py
sanic/static.py
sanic/testing.py
sanic/utils.py
sanic/views.py
sanic/websocket.py
sanic/worker.py
sanic_patched.egg-info/PKG-INFO
sanic_patched.egg-info/SOURCES.txt
sanic_patched.egg-info/dependency_links.txt
sanic_patched.egg-info/requires.txt
sanic_patched.egg-info/top_level.txt