Metadata-Version: 1.1
Name: sanic-patched
Version: 0.4.1
Summary: A microframework based on uvloop, httptools, and learnings of flask
Home-page: http://github.com/channelcat/sanic/
Author: Channel Cat
Author-email: channelcat@gmail.com
License: MIT
Platform: any
Classifier: Development Status :: 2 - Pre-Alpha
Classifier: Environment :: Web Environment
Classifier: License :: OSI Approved :: MIT License
Classifier: Programming Language :: Python :: 3.5
Classifier: Programming Language :: Python :: 3.6
